owa/env/gst/__init__.py
owa/env/gst/mkv_reader.py
owa/env/gst/gst-plugins/README.md
owa/env/gst/gst-plugins/python/py_utctimestampsrc.py
owa/env/gst/gst_runner/__init__.py
owa/env/gst/gst_runner/extensions.py
owa/env/gst/gst_runner/gst_runner.py
owa/env/gst/omnimodal/__init__.py
owa/env/gst/omnimodal/appsink_recorder.py
owa/env/gst/omnimodal/subprocess_recorder.py
owa/env/gst/pipeline_builder/__init__.py
owa/env/gst/pipeline_builder/element.py
owa/env/gst/pipeline_builder/factory.py
owa/env/gst/pipeline_builder/pipeline.py
owa/env/gst/screen/__init__.py
owa/env/gst/screen/listeners.py
owa/env/gst/screen/runnable.py
owa/env/gst/utils/__init__.py
owa/env/gst/utils/gst_lifecycle.py
owa/env/gst/utils/gst_sample_postprocess.py
owa/env/gst/utils/misc.py
owa/env/plugins/gst.py
owa_env_gst-0.6.5.dist-info/METADATA
owa_env_gst-0.6.5.dist-info/WHEEL
owa_env_gst-0.6.5.dist-info/entry_points.txt
owa_env_gst-0.6.5.dist-info/RECORD
