Metadata-Version: 2.4
Name: owa-env-gst
Version: 0.6.5
Summary: High-performance GStreamer-based screen capture plugin for Open World Agents
License: MIT
Requires-Python: >=3.11
Requires-Dist: av>=15.0
Requires-Dist: loguru
Requires-Dist: mediaref~=0.4.1
Requires-Dist: numpy>=2.0
Requires-Dist: opencv-python
Requires-Dist: owa-core==0.6.5
Requires-Dist: owa-msgs==0.6.5
Requires-Dist: pygobject-stubs
Requires-Dist: tqdm
